inhibit/__init__.py
inhibit/inhibit.py
inhibit-0.1.0.dist-info/licenses/LICENSE
inhibit-0.1.0.dist-info/WHEEL
inhibit-0.1.0.dist-info/entry_points.txt
inhibit-0.1.0.dist-info/METADATA
inhibit-0.1.0.dist-info/RECORD
