Metadata-Version: 2.4
Name: inhibit
Version: 0.1.0
Summary: System suspend inhibitor
Author: Juha Heljoranta
Author-email: Juha Heljoranta <juha.heljoranta@iki.fi>
License-Expression: Apache-2.0
License-File: LICENSE
Classifier: Development Status :: 4 - Beta
Classifier: Environment :: Console
Classifier: Intended Audience :: Developers
Classifier: Operating System :: POSIX :: Linux
Requires-Python: >=3.14
Project-URL: Homepage, https://codeberg.org/jooth/inhibit
Project-URL: Issues, https://codeberg.org/jooth/inhibit/issues
